padtexturetool/__init__.py
padtexturetool/__main__.py
padtexturetool/encoding.py
padtexturetool/extract.py
padtexturetool/settings.py
padtexturetool/texture.py
padtexturetool/texture_reader.py
padtexturetool/texture_writer.py
padtexturetool-1.1.4.dist-info/LICENSE
padtexturetool-1.1.4.dist-info/METADATA
padtexturetool-1.1.4.dist-info/WHEEL
padtexturetool-1.1.4.dist-info/top_level.txt
padtexturetool-1.1.4.dist-info/RECORD
