Metadata-Version: 2.1
Name: padtexturetool
Version: 1.1.4
Summary: A tool to extract textures from PAD
Home-page: https://github.com/TsubakiBotPad/padtexturetool
Author: Cody Watts and Aradia
Author-email: 69992611+TsubakiBotPad@users.noreply.github.com
License: MIT
Classifier: Programming Language :: Python :: 3
Classifier: License :: OSI Approved :: MIT License
Classifier: Operating System :: OS Independent
Requires-Python: >=3.8
License-File: LICENSE
Requires-Dist: pypng (==0.0.20)
Requires-Dist: crc
